<?xml version="1.0" encoding="windows-1252"?>
<XMI xmi.version="1.1" xmlns:UML="omg.org/UML1.3">
	<XMI.header><XMI.documentation><XMI.exporter>Enterprise Architect</XMI.exporter><XMI.exporterVersion>2.5</XMI.exporterVersion></XMI.documentation></XMI.header><XMI.content><UML:Model name="EA Model" xmi.id="MX_EAID_CFD82DA7_4FEB_4f43_BC11_4CC7A52F389D"><UML:Namespace.ownedElement><UML:Class name="EARootClass" xmi.id="EAID_11111111_5487_4080_A7F4_41526CB0AA00" isRoot="true" isLeaf="false" isAbstract="false"/><UML:Package name="operations" xmi.id="EAPK_CFD82DA7_4FEB_4f43_BC11_4CC7A52F389D" isRoot="false" isLeaf="false" isAbstract="false" visibility="public"><UML:ModelElement.taggedValue><UML:TaggedValue tag="parent" value="EAPK_D04C1C19_9EB1_4c3d_87F7_EF581A198AC1"/><UML:TaggedValue tag="created" value="2017-12-26 13:53:50"/><UML:TaggedValue tag="modified" value="2017-12-26 13:53:50"/><UML:TaggedValue tag="iscontrolled" value="TRUE"/><UML:TaggedValue tag="xmlpath" value="ea4\4CC7A52F389D.xml"/><UML:TaggedValue tag="version" value="1.0"/><UML:TaggedValue tag="isprotected" value="FALSE"/><UML:TaggedValue tag="usedtd" value="FALSE"/><UML:TaggedValue tag="logxml" value="FALSE"/><UML:TaggedValue tag="packageFlags" value="VCCFG=SKLD;CRC=0;"/><UML:TaggedValue tag="phase" value="1.0"/><UML:TaggedValue tag="status" value="Proposed"/><UML:TaggedValue tag="author" value="husekjos"/><UML:TaggedValue tag="complexity" value="1"/><UML:TaggedValue tag="ea_stype" value="Public"/><UML:TaggedValue tag="tpos" value="0"/><UML:TaggedValue tag="gentype" value="Java"/></UML:ModelElement.taggedValue><UML:Namespace.ownedElement><UML:Class name="ProductOperations" xmi.id="EAID_123B8F3D_2661_4149_93CC_65EFB8861BAE" visibility="public" namespace="EAPK_CFD82DA7_4FEB_4f43_BC11_4CC7A52F389D" isRoot="false" isLeaf="false" isAbstract="false" isActive="false"><UML:ModelElement.taggedValue><UML:TaggedValue tag="documentation" value="Implementuje operace souvisejici s produkty."/><UML:TaggedValue tag="isSpecification" value="false"/><UML:TaggedValue tag="ea_stype" value="Class"/><UML:TaggedValue tag="ea_ntype" value="0"/><UML:TaggedValue tag="version" value="1.0"/><UML:TaggedValue tag="package" value="EAPK_CFD82DA7_4FEB_4f43_BC11_4CC7A52F389D"/><UML:TaggedValue tag="date_created" value="2017-12-26 13:53:51"/><UML:TaggedValue tag="date_modified" value="2017-12-26 13:53:51"/><UML:TaggedValue tag="genfile" value="C:\Users\Pepa\Desktop\School\SI\repo\src\api\src\main\java\cz\cvut\fit\project\skld\application\operations\ProductOperations.java"/><UML:TaggedValue tag="gentype" value="Java"/><UML:TaggedValue tag="tagged" value="0"/><UML:TaggedValue tag="package_name" value="operations"/><UML:TaggedValue tag="phase" value="1.0"/><UML:TaggedValue tag="author" value="husekjos"/><UML:TaggedValue tag="complexity" value="1"/><UML:TaggedValue tag="status" value="Proposed"/><UML:TaggedValue tag="tpos" value="0"/><UML:TaggedValue tag="ea_localid" value="4111"/><UML:TaggedValue tag="ea_eleType" value="element"/><UML:TaggedValue tag="eventflags" value="OBJ=5abb;"/><UML:TaggedValue tag="$ea_attsclassified" value="{331FC4C1-E47C-42a2-AEB2-926BC97BCBFB},{4DAD135D-E955-4aa2-A890-96CCF017648E}"/><UML:TaggedValue tag="$ea_oprparamsclassified" value="{BBF3759F-12A6-4968-8D4E-0DAB3721CBC1},{C3D97A40-267C-43ec-9D6E-773E36DC82B2}"/><UML:TaggedValue tag="style" value="BackColor=-1;BorderColor=-1;BorderWidth=-1;FontColor=-1;VSwimLanes=1;HSwimLanes=1;BorderStyle=0;"/></UML:ModelElement.taggedValue><UML:Classifier.feature><UML:Attribute name="LOGGER" changeable="frozen" visibility="private" ownerScope="instance" targetScope="instance"><UML:Attribute.initialValue><UML:Expression body="LoggerFactory.getLogger(ProductOperations.class)"/></UML:Attribute.initialValue><UML:StructuralFeature.type><UML:Classifier xmi.idref="eaxmiid0"/></UML:StructuralFeature.type><UML:ModelElement.taggedValue><UML:TaggedValue tag="type" value="Logger"/><UML:TaggedValue tag="derived" value="0"/><UML:TaggedValue tag="containment" value="Not Specified"/><UML:TaggedValue tag="length" value="0"/><UML:TaggedValue tag="ordered" value="0"/><UML:TaggedValue tag="static" value="1"/><UML:TaggedValue tag="collection" value="false"/><UML:TaggedValue tag="position" value="0"/><UML:TaggedValue tag="lowerBound" value="1"/><UML:TaggedValue tag="upperBound" value="1"/><UML:TaggedValue tag="duplicates" value="0"/><UML:TaggedValue tag="ea_guid" value="{1AFA7040-710E-469b-86A4-B7F8E3684AF7}"/><UML:TaggedValue tag="ea_localid" value="1214"/><UML:TaggedValue tag="styleex" value="volatile=0;union=0;"/></UML:ModelElement.taggedValue></UML:Attribute><UML:Attribute name="positionDAO" changeable="frozen" visibility="private" ownerScope="instance" targetScope="instance"><UML:Attribute.initialValue><UML:Expression/></UML:Attribute.initialValue><UML:StructuralFeature.type><UML:Classifier xmi.idref="EAID_E860FEA8_FD81_45b6_87EC_8D23F214484B"/></UML:StructuralFeature.type><UML:ModelElement.taggedValue><UML:TaggedValue tag="type" value="PositionDAO"/><UML:TaggedValue tag="derived" value="0"/><UML:TaggedValue tag="containment" value="Not Specified"/><UML:TaggedValue tag="length" value="0"/><UML:TaggedValue tag="ordered" value="0"/><UML:TaggedValue tag="collection" value="false"/><UML:TaggedValue tag="position" value="2"/><UML:TaggedValue tag="lowerBound" value="1"/><UML:TaggedValue tag="upperBound" value="1"/><UML:TaggedValue tag="duplicates" value="0"/><UML:TaggedValue tag="ea_guid" value="{0D98E1F3-49D0-4141-B7B4-57FEC3986C29}"/><UML:TaggedValue tag="ea_localid" value="1215"/><UML:TaggedValue tag="styleex" value="volatile=0;union=0;"/></UML:ModelElement.taggedValue></UML:Attribute><UML:Attribute name="productDAO" changeable="frozen" visibility="private" ownerScope="instance" targetScope="instance"><UML:Attribute.initialValue><UML:Expression/></UML:Attribute.initialValue><UML:StructuralFeature.type><UML:Classifier xmi.idref="EAID_5F9E8C93_59DC_42bb_8209_3611D2544AB8"/></UML:StructuralFeature.type><UML:ModelElement.taggedValue><UML:TaggedValue tag="type" value="ProductDAO"/><UML:TaggedValue tag="derived" value="0"/><UML:TaggedValue tag="containment" value="Not Specified"/><UML:TaggedValue tag="length" value="0"/><UML:TaggedValue tag="ordered" value="0"/><UML:TaggedValue tag="collection" value="false"/><UML:TaggedValue tag="position" value="1"/><UML:TaggedValue tag="lowerBound" value="1"/><UML:TaggedValue tag="upperBound" value="1"/><UML:TaggedValue tag="duplicates" value="0"/><UML:TaggedValue tag="ea_guid" value="{79B40960-F3F0-4665-8CDD-8F4553A7338A}"/><UML:TaggedValue tag="ea_localid" value="1216"/><UML:TaggedValue tag="styleex" value="volatile=0;union=0;"/></UML:ModelElement.taggedValue></UML:Attribute><UML:Operation name="create" visibility="public" ownerScope="instance" isQuery="false" concurrency="sequential"><UML:ModelElement.taggedValue><UML:TaggedValue tag="documentation" value="Vytvori novy produkt.&#xA;@return Vytvoreny produkt (vcetne pripadnych automaticky generovanych hodnot)"/><UML:TaggedValue tag="type" value="Product"/><UML:TaggedValue tag="const" value="false"/><UML:TaggedValue tag="synchronised" value="0"/><UML:TaggedValue tag="concurrency" value="Sequential"/><UML:TaggedValue tag="position" value="1"/><UML:TaggedValue tag="returnarray" value="0"/><UML:TaggedValue tag="pure" value="0"/><UML:TaggedValue tag="ea_guid" value="{4F3F6EA9-61A9-4653-AEFA-7AE2DDEDC287}"/><UML:TaggedValue tag="ea_localid" value="2410"/><UML:TaggedValue tag="throws" value="InvalidStateException" xmi.id="EAID_EAE37CDA_27AF_44c0_B385_0D9930031473"><XMI.extension xmi.extender="Enterprise Architect 2.5"><UML:Comment name="@exception InvalidStateException Produkt se stejnym ID jiz v databazi existuje"/></XMI.extension></UML:TaggedValue></UML:ModelElement.taggedValue><UML:BehavioralFeature.parameter><UML:Parameter kind="return" visibility="public"><UML:Parameter.type><UML:Classifier xmi.idref="EAID_4552AA43_0F22_48d8_990C_9F55C34EAFA2"/></UML:Parameter.type><UML:ModelElement.taggedValue><UML:TaggedValue tag="pos" value="0"/><UML:TaggedValue tag="type" value="Product"/><UML:TaggedValue tag="const" value="0"/><UML:TaggedValue tag="classifier" value="EAID_4552AA43_0F22_48d8_990C_9F55C34EAFA2"/><UML:TaggedValue tag="ea_guid" value="{RETURNID-61A9-4653-AEFA-7AE2DDEDC287}"/></UML:ModelElement.taggedValue><UML:Parameter.defaultValue><UML:Expression/></UML:Parameter.defaultValue></UML:Parameter><UML:Parameter name="creator" kind="in" visibility="public"><UML:Parameter.type><UML:Classifier xmi.idref="EAID_E971BBB6_4C2F_4889_87F4_D5837581E3DB"/></UML:Parameter.type><UML:ModelElement.taggedValue><UML:TaggedValue tag="note" value="Uzivatel, ktery operaci zadal do systemu"/><UML:TaggedValue tag="pos" value="0"/><UML:TaggedValue tag="type" value="User"/><UML:TaggedValue tag="const" value="0"/><UML:TaggedValue tag="classifier" value="EAID_E971BBB6_4C2F_4889_87F4_D5837581E3DB"/><UML:TaggedValue tag="ea_guid" value="{1B01E61B-3100-465e-842C-59BCE3609E19}"/></UML:ModelElement.taggedValue><UML:Parameter.defaultValue><UML:Expression/></UML:Parameter.defaultValue></UML:Parameter><UML:Parameter name="product" kind="in" visibility="public"><UML:Parameter.type><UML:Classifier xmi.idref="eaxmiid1"/></UML:Parameter.type><UML:ModelElement.taggedValue><UML:TaggedValue tag="note" value="Objekt obsahujici informace, podle kterych bude produkt vytvoren"/><UML:TaggedValue tag="pos" value="1"/><UML:TaggedValue tag="type" value="ProductChange"/><UML:TaggedValue tag="const" value="0"/><UML:TaggedValue tag="ea_guid" value="{2A9F3643-F18B-42d5-B29C-C528395E6BA4}"/></UML:ModelElement.taggedValue><UML:Parameter.defaultValue><UML:Expression/></UML:Parameter.defaultValue></UML:Parameter></UML:BehavioralFeature.parameter></UML:Operation><UML:Operation name="edit" visibility="public" ownerScope="instance" isQuery="false" concurrency="sequential"><UML:ModelElement.taggedValue><UML:TaggedValue tag="documentation" value="Zmeni nazev produktu se zadanym ID."/><UML:TaggedValue tag="type" value="Product"/><UML:TaggedValue tag="const" value="false"/><UML:TaggedValue tag="synchronised" value="0"/><UML:TaggedValue tag="concurrency" value="Sequential"/><UML:TaggedValue tag="position" value="4"/><UML:TaggedValue tag="returnarray" value="0"/><UML:TaggedValue tag="pure" value="0"/><UML:TaggedValue tag="ea_guid" value="{96DA1BEF-334F-45a9-8514-086E22BC90DC}"/><UML:TaggedValue tag="ea_localid" value="2411"/><UML:TaggedValue tag="throws" value="NotFoundException" xmi.id="EAID_C63D029F_FA45_417e_892C_0FB83F6F3799"><XMI.extension xmi.extender="Enterprise Architect 2.5"><UML:Comment name="@exception NotFoundException Produkt se zadanym ID v systemu neexistuje"/></XMI.extension></UML:TaggedValue></UML:ModelElement.taggedValue><UML:BehavioralFeature.parameter><UML:Parameter kind="return" visibility="public"><UML:Parameter.type><UML:Classifier xmi.idref="EAID_4552AA43_0F22_48d8_990C_9F55C34EAFA2"/></UML:Parameter.type><UML:ModelElement.taggedValue><UML:TaggedValue tag="pos" value="0"/><UML:TaggedValue tag="type" value="Product"/><UML:TaggedValue tag="const" value="0"/><UML:TaggedValue tag="classifier" value="EAID_4552AA43_0F22_48d8_990C_9F55C34EAFA2"/><UML:TaggedValue tag="ea_guid" value="{RETURNID-334F-45a9-8514-086E22BC90DC}"/></UML:ModelElement.taggedValue><UML:Parameter.defaultValue><UML:Expression/></UML:Parameter.defaultValue></UML:Parameter><UML:Parameter name="change" kind="in" visibility="public"><UML:Parameter.type><UML:Classifier xmi.idref="eaxmiid1"/></UML:Parameter.type><UML:ModelElement.taggedValue><UML:TaggedValue tag="note" value="Objekt obsahujici informace, podle kterych bude produkt zmenen"/><UML:TaggedValue tag="pos" value="0"/><UML:TaggedValue tag="type" value="ProductChange"/><UML:TaggedValue tag="const" value="0"/><UML:TaggedValue tag="ea_guid" value="{59274789-657C-4380-8088-FBB7684B0F9F}"/></UML:ModelElement.taggedValue><UML:Parameter.defaultValue><UML:Expression/></UML:Parameter.defaultValue></UML:Parameter></UML:BehavioralFeature.parameter></UML:Operation><UML:Operation name="get" visibility="public" ownerScope="instance" isQuery="false" concurrency="sequential"><UML:ModelElement.taggedValue><UML:TaggedValue tag="documentation" value="Vraci produkt se zadanym ID.&#xA;@return Pozadovany produkt"/><UML:TaggedValue tag="type" value="Product"/><UML:TaggedValue tag="const" value="false"/><UML:TaggedValue tag="synchronised" value="0"/><UML:TaggedValue tag="concurrency" value="Sequential"/><UML:TaggedValue tag="position" value="3"/><UML:TaggedValue tag="returnarray" value="0"/><UML:TaggedValue tag="pure" value="0"/><UML:TaggedValue tag="ea_guid" value="{B0260B9F-ECC0-43e4-9D7E-3046650C5840}"/><UML:TaggedValue tag="ea_localid" value="2412"/><UML:TaggedValue tag="throws" value="NotFoundException" xmi.id="EAID_D100B5DE_3F1D_4c21_B284_A54EDF82BAA5"><XMI.extension xmi.extender="Enterprise Architect 2.5"><UML:Comment name="@exception NotFoundException Produkt se zadanym ID v systemu neexistuje"/></XMI.extension></UML:TaggedValue></UML:ModelElement.taggedValue><UML:BehavioralFeature.parameter><UML:Parameter kind="return" visibility="public"><UML:Parameter.type><UML:Classifier xmi.idref="EAID_4552AA43_0F22_48d8_990C_9F55C34EAFA2"/></UML:Parameter.type><UML:ModelElement.taggedValue><UML:TaggedValue tag="pos" value="0"/><UML:TaggedValue tag="type" value="Product"/><UML:TaggedValue tag="const" value="0"/><UML:TaggedValue tag="classifier" value="EAID_4552AA43_0F22_48d8_990C_9F55C34EAFA2"/><UML:TaggedValue tag="ea_guid" value="{RETURNID-ECC0-43e4-9D7E-3046650C5840}"/></UML:ModelElement.taggedValue><UML:Parameter.defaultValue><UML:Expression/></UML:Parameter.defaultValue></UML:Parameter><UML:Parameter name="id" kind="in" visibility="public"><UML:Parameter.type><UML:Classifier xmi.idref="eaxmiid2"/></UML:Parameter.type><UML:ModelElement.taggedValue><UML:TaggedValue tag="note" value="ID produktu"/><UML:TaggedValue tag="pos" value="0"/><UML:TaggedValue tag="type" value="long"/><UML:TaggedValue tag="const" value="0"/><UML:TaggedValue tag="ea_guid" value="{C5CAAAEF-ACEF-4de2-BB95-BFC29CD1E611}"/></UML:ModelElement.taggedValue><UML:Parameter.defaultValue><UML:Expression/></UML:Parameter.defaultValue></UML:Parameter></UML:BehavioralFeature.parameter></UML:Operation><UML:Operation name="list" visibility="public" ownerScope="instance" isQuery="false" concurrency="sequential"><UML:ModelElement.taggedValue><UML:TaggedValue tag="documentation" value="Get a list of all the products that are in the database&#xA;@return a list of all the products that are in the database"/><UML:TaggedValue tag="type" value="List&lt;Product&gt;"/><UML:TaggedValue tag="const" value="false"/><UML:TaggedValue tag="synchronised" value="0"/><UML:TaggedValue tag="concurrency" value="Sequential"/><UML:TaggedValue tag="position" value="2"/><UML:TaggedValue tag="returnarray" value="0"/><UML:TaggedValue tag="pure" value="0"/><UML:TaggedValue tag="ea_guid" value="{FEA12ACF-396B-4275-BCA7-C6DAA737887D}"/><UML:TaggedValue tag="ea_localid" value="2413"/></UML:ModelElement.taggedValue><UML:BehavioralFeature.parameter><UML:Parameter kind="return" visibility="public"><UML:Parameter.type><UML:Classifier xmi.idref="eaxmiid3"/></UML:Parameter.type><UML:ModelElement.taggedValue><UML:TaggedValue tag="pos" value="0"/><UML:TaggedValue tag="type" value="List&lt;Product&gt;"/><UML:TaggedValue tag="const" value="0"/><UML:TaggedValue tag="ea_guid" value="{RETURNID-396B-4275-BCA7-C6DAA737887D}"/></UML:ModelElement.taggedValue><UML:Parameter.defaultValue><UML:Expression/></UML:Parameter.defaultValue></UML:Parameter></UML:BehavioralFeature.parameter></UML:Operation><UML:Operation name="positionsForProduct" visibility="public" ownerScope="instance" isQuery="false" concurrency="sequential"><UML:ModelElement.taggedValue><UML:TaggedValue tag="documentation" value="Vraci seznam pozic, na kterych je produkt ve skladu umisten.&#xA;@returna Seznam pozic"/><UML:TaggedValue tag="type" value="List&lt;ProductPosition&gt;"/><UML:TaggedValue tag="const" value="false"/><UML:TaggedValue tag="synchronised" value="0"/><UML:TaggedValue tag="concurrency" value="Sequential"/><UML:TaggedValue tag="position" value="5"/><UML:TaggedValue tag="returnarray" value="0"/><UML:TaggedValue tag="pure" value="0"/><UML:TaggedValue tag="ea_guid" value="{6316DFC6-8F5F-4368-8EB3-4C3F2B325230}"/><UML:TaggedValue tag="ea_localid" value="2414"/></UML:ModelElement.taggedValue><UML:BehavioralFeature.parameter><UML:Parameter kind="return" visibility="public"><UML:Parameter.type><UML:Classifier xmi.idref="eaxmiid4"/></UML:Parameter.type><UML:ModelElement.taggedValue><UML:TaggedValue tag="pos" value="0"/><UML:TaggedValue tag="type" value="List&lt;ProductPosition&gt;"/><UML:TaggedValue tag="const" value="0"/><UML:TaggedValue tag="ea_guid" value="{RETURNID-8F5F-4368-8EB3-4C3F2B325230}"/></UML:ModelElement.taggedValue><UML:Parameter.defaultValue><UML:Expression/></UML:Parameter.defaultValue></UML:Parameter><UML:Parameter name="id" kind="in" visibility="public"><UML:Parameter.type><UML:Classifier xmi.idref="eaxmiid2"/></UML:Parameter.type><UML:ModelElement.taggedValue><UML:TaggedValue tag="note" value="ID produktu"/><UML:TaggedValue tag="pos" value="0"/><UML:TaggedValue tag="type" value="long"/><UML:TaggedValue tag="const" value="0"/><UML:TaggedValue tag="ea_guid" value="{D2559B94-EEAD-48f4-85A0-EB7EDE07368A}"/></UML:ModelElement.taggedValue><UML:Parameter.defaultValue><UML:Expression/></UML:Parameter.defaultValue></UML:Parameter></UML:BehavioralFeature.parameter></UML:Operation><UML:Operation name="ProductOperations" visibility="public" ownerScope="instance" isQuery="false" concurrency="sequential"><UML:ModelElement.taggedValue><UML:TaggedValue tag="documentation" value="Konstruktor."/><UML:TaggedValue tag="const" value="false"/><UML:TaggedValue tag="synchronised" value="0"/><UML:TaggedValue tag="concurrency" value="Sequential"/><UML:TaggedValue tag="position" value="0"/><UML:TaggedValue tag="returnarray" value="0"/><UML:TaggedValue tag="pure" value="0"/><UML:TaggedValue tag="ea_guid" value="{C2D3C3EF-F950-41ce-9136-2FA5E3A8E0FB}"/><UML:TaggedValue tag="ea_localid" value="2415"/></UML:ModelElement.taggedValue><UML:BehavioralFeature.parameter><UML:Parameter kind="return" visibility="public"><UML:Parameter.type><UML:Classifier xmi.idref="eaxmiid5"/></UML:Parameter.type><UML:ModelElement.taggedValue><UML:TaggedValue tag="pos" value="0"/><UML:TaggedValue tag="const" value="0"/><UML:TaggedValue tag="ea_guid" value="{RETURNID-F950-41ce-9136-2FA5E3A8E0FB}"/></UML:ModelElement.taggedValue><UML:Parameter.defaultValue><UML:Expression/></UML:Parameter.defaultValue></UML:Parameter><UML:Parameter name="pDao" kind="in" visibility="public"><UML:Parameter.type><UML:Classifier xmi.idref="EAID_5F9E8C93_59DC_42bb_8209_3611D2544AB8"/></UML:Parameter.type><UML:ModelElement.taggedValue><UML:TaggedValue tag="note" value="DAO pro pristup k produktum"/><UML:TaggedValue tag="pos" value="0"/><UML:TaggedValue tag="type" value="ProductDAO"/><UML:TaggedValue tag="const" value="0"/><UML:TaggedValue tag="classifier" value="EAID_5F9E8C93_59DC_42bb_8209_3611D2544AB8"/><UML:TaggedValue tag="ea_guid" value="{D690484B-E3EC-4d89-A19A-D5143685BD4C}"/></UML:ModelElement.taggedValue><UML:Parameter.defaultValue><UML:Expression/></UML:Parameter.defaultValue></UML:Parameter><UML:Parameter name="posDao" kind="in" visibility="public"><UML:Parameter.type><UML:Classifier xmi.idref="EAID_E860FEA8_FD81_45b6_87EC_8D23F214484B"/></UML:Parameter.type><UML:ModelElement.taggedValue><UML:TaggedValue tag="note" value="DAO pro pristup k pozicim"/><UML:TaggedValue tag="pos" value="1"/><UML:TaggedValue tag="type" value="PositionDAO"/><UML:TaggedValue tag="const" value="0"/><UML:TaggedValue tag="classifier" value="EAID_E860FEA8_FD81_45b6_87EC_8D23F214484B"/><UML:TaggedValue tag="ea_guid" value="{1FB9F9B1-4040-44fc-BD06-CC6296F337C5}"/></UML:ModelElement.taggedValue><UML:Parameter.defaultValue><UML:Expression/></UML:Parameter.defaultValue></UML:Parameter></UML:BehavioralFeature.parameter></UML:Operation></UML:Classifier.feature></UML:Class><UML:Association xmi.id="EAID_136085B6_6484_4dee_9098_38DC6E15B4A6" visibility="public" isRoot="false" isLeaf="false" isAbstract="false"><UML:ModelElement.taggedValue><UML:TaggedValue tag="style" value="3"/><UML:TaggedValue tag="ea_type" value="Association"/><UML:TaggedValue tag="direction" value="Source -&gt; Destination"/><UML:TaggedValue tag="linemode" value="3"/><UML:TaggedValue tag="linecolor" value="-1"/><UML:TaggedValue tag="linewidth" value="0"/><UML:TaggedValue tag="seqno" value="0"/><UML:TaggedValue tag="headStyle" value="0"/><UML:TaggedValue tag="lineStyle" value="0"/><UML:TaggedValue tag="ea_localid" value="2777"/><UML:TaggedValue tag="ea_sourceName" value="ProductResource"/><UML:TaggedValue tag="ea_targetName" value="ProductOperations"/><UML:TaggedValue tag="ea_sourceType" value="Class"/><UML:TaggedValue tag="ea_targetType" value="Class"/><UML:TaggedValue tag="ea_sourceID" value="4116"/><UML:TaggedValue tag="ea_targetID" value="4111"/><UML:TaggedValue tag="virtualInheritance" value="0"/><UML:TaggedValue tag="rt" value="~productOps"/></UML:ModelElement.taggedValue><UML:Association.connection><UML:AssociationEnd visibility="public" aggregation="none" isOrdered="false" targetScope="instance" changeable="none" isNavigable="false" type="EAID_201D76DC_417E_47f1_B8F2_53871408F064"><UML:ModelElement.taggedValue><UML:TaggedValue tag="containment" value="Unspecified"/><UML:TaggedValue tag="sourcestyle" value="Union=0;Derived=0;AllowDuplicates=0;Owned=0;Navigable=Non-Navigable;"/><UML:TaggedValue tag="ea_end" value="source"/></UML:ModelElement.taggedValue></UML:AssociationEnd><UML:AssociationEnd visibility="protected" name="productOps" aggregation="none" isOrdered="false" targetScope="instance" changeable="none" isNavigable="true" type="EAID_123B8F3D_2661_4149_93CC_65EFB8861BAE"><UML:ModelElement.taggedValue><UML:TaggedValue tag="containment" value="Unspecified"/><UML:TaggedValue tag="type" value="Package"/><UML:TaggedValue tag="deststyle" value="Union=0;Derived=0;AllowDuplicates=0;Owned=0;Navigable=Navigable;"/><UML:TaggedValue tag="ea_end" value="target"/><UML:TaggedValue tag="scope" value="Package"/></UML:ModelElement.taggedValue></UML:AssociationEnd></UML:Association.connection></UML:Association><UML:Association xmi.id="EAID_C24AB116_0D1D_482a_92EE_A02B71354B65" visibility="public" isRoot="false" isLeaf="false" isAbstract="false"><UML:ModelElement.taggedValue><UML:TaggedValue tag="style" value="3"/><UML:TaggedValue tag="ea_type" value="Association"/><UML:TaggedValue tag="direction" value="Source -&gt; Destination"/><UML:TaggedValue tag="linemode" value="3"/><UML:TaggedValue tag="linecolor" value="-1"/><UML:TaggedValue tag="linewidth" value="0"/><UML:TaggedValue tag="seqno" value="0"/><UML:TaggedValue tag="headStyle" value="0"/><UML:TaggedValue tag="lineStyle" value="0"/><UML:TaggedValue tag="ea_localid" value="2771"/><UML:TaggedValue tag="ea_sourceName" value="ProductOperations"/><UML:TaggedValue tag="ea_targetName" value="PositionDAO"/><UML:TaggedValue tag="ea_sourceType" value="Class"/><UML:TaggedValue tag="ea_targetType" value="Interface"/><UML:TaggedValue tag="ea_sourceID" value="4111"/><UML:TaggedValue tag="ea_targetID" value="4101"/><UML:TaggedValue tag="virtualInheritance" value="0"/><UML:TaggedValue tag="rt" value="-positionDAO"/></UML:ModelElement.taggedValue><UML:Association.connection><UML:AssociationEnd visibility="public" aggregation="none" isOrdered="false" targetScope="instance" changeable="none" isNavigable="false" type="EAID_123B8F3D_2661_4149_93CC_65EFB8861BAE"><UML:ModelElement.taggedValue><UML:TaggedValue tag="containment" value="Unspecified"/><UML:TaggedValue tag="sourcestyle" value="Union=0;Derived=0;AllowDuplicates=0;Owned=0;Navigable=Non-Navigable;"/><UML:TaggedValue tag="ea_end" value="source"/></UML:ModelElement.taggedValue></UML:AssociationEnd><UML:AssociationEnd visibility="private" name="positionDAO" aggregation="none" isOrdered="false" targetScope="instance" changeable="none" isNavigable="true" type="EAID_E860FEA8_FD81_45b6_87EC_8D23F214484B"><UML:ModelElement.taggedValue><UML:TaggedValue tag="containment" value="Unspecified"/><UML:TaggedValue tag="type" value="Private"/><UML:TaggedValue tag="deststyle" value="Union=0;Derived=0;AllowDuplicates=0;Owned=0;Navigable=Navigable;"/><UML:TaggedValue tag="ea_end" value="target"/></UML:ModelElement.taggedValue></UML:AssociationEnd></UML:Association.connection></UML:Association><UML:Association xmi.id="EAID_D8828740_5957_427b_8308_AC853DB3C5B8" visibility="public" isRoot="false" isLeaf="false" isAbstract="false"><UML:ModelElement.taggedValue><UML:TaggedValue tag="style" value="3"/><UML:TaggedValue tag="ea_type" value="Association"/><UML:TaggedValue tag="direction" value="Source -&gt; Destination"/><UML:TaggedValue tag="linemode" value="3"/><UML:TaggedValue tag="linecolor" value="-1"/><UML:TaggedValue tag="linewidth" value="0"/><UML:TaggedValue tag="seqno" value="0"/><UML:TaggedValue tag="headStyle" value="0"/><UML:TaggedValue tag="lineStyle" value="0"/><UML:TaggedValue tag="ea_localid" value="2772"/><UML:TaggedValue tag="ea_sourceName" value="ProductOperations"/><UML:TaggedValue tag="ea_targetName" value="ProductDAO"/><UML:TaggedValue tag="ea_sourceType" value="Class"/><UML:TaggedValue tag="ea_targetType" value="Interface"/><UML:TaggedValue tag="ea_sourceID" value="4111"/><UML:TaggedValue tag="ea_targetID" value="4102"/><UML:TaggedValue tag="virtualInheritance" value="0"/><UML:TaggedValue tag="rt" value="-productDAO"/></UML:ModelElement.taggedValue><UML:Association.connection><UML:AssociationEnd visibility="public" aggregation="none" isOrdered="false" targetScope="instance" changeable="none" isNavigable="false" type="EAID_123B8F3D_2661_4149_93CC_65EFB8861BAE"><UML:ModelElement.taggedValue><UML:TaggedValue tag="containment" value="Unspecified"/><UML:TaggedValue tag="sourcestyle" value="Union=0;Derived=0;AllowDuplicates=0;Owned=0;Navigable=Non-Navigable;"/><UML:TaggedValue tag="ea_end" value="source"/></UML:ModelElement.taggedValue></UML:AssociationEnd><UML:AssociationEnd visibility="private" name="productDAO" aggregation="none" isOrdered="false" targetScope="instance" changeable="none" isNavigable="true" type="EAID_5F9E8C93_59DC_42bb_8209_3611D2544AB8"><UML:ModelElement.taggedValue><UML:TaggedValue tag="containment" value="Unspecified"/><UML:TaggedValue tag="type" value="Private"/><UML:TaggedValue tag="deststyle" value="Union=0;Derived=0;AllowDuplicates=0;Owned=0;Navigable=Navigable;"/><UML:TaggedValue tag="ea_end" value="target"/></UML:ModelElement.taggedValue></UML:AssociationEnd></UML:Association.connection></UML:Association><UML:Association xmi.id="EAID_E4BDF459_D3A8_4f6a_8274_5473A47F5D12" visibility="public" isRoot="false" isLeaf="false" isAbstract="false"><UML:ModelElement.taggedValue><UML:TaggedValue tag="style" value="3"/><UML:TaggedValue tag="ea_type" value="Association"/><UML:TaggedValue tag="direction" value="Source -&gt; Destination"/><UML:TaggedValue tag="linemode" value="3"/><UML:TaggedValue tag="linecolor" value="-1"/><UML:TaggedValue tag="linewidth" value="0"/><UML:TaggedValue tag="seqno" value="0"/><UML:TaggedValue tag="headStyle" value="0"/><UML:TaggedValue tag="lineStyle" value="0"/><UML:TaggedValue tag="ea_localid" value="2778"/><UML:TaggedValue tag="ea_sourceName" value="ProductsResource"/><UML:TaggedValue tag="ea_targetName" value="ProductOperations"/><UML:TaggedValue tag="ea_sourceType" value="Class"/><UML:TaggedValue tag="ea_targetType" value="Class"/><UML:TaggedValue tag="ea_sourceID" value="4117"/><UML:TaggedValue tag="ea_targetID" value="4111"/><UML:TaggedValue tag="virtualInheritance" value="0"/><UML:TaggedValue tag="rt" value="-productOps"/></UML:ModelElement.taggedValue><UML:Association.connection><UML:AssociationEnd visibility="public" aggregation="none" isOrdered="false" targetScope="instance" changeable="none" isNavigable="false" type="EAID_FF35AD95_8EE4_4877_BCC0_870E6D72A614"><UML:ModelElement.taggedValue><UML:TaggedValue tag="containment" value="Unspecified"/><UML:TaggedValue tag="sourcestyle" value="Union=0;Derived=0;AllowDuplicates=0;Owned=0;Navigable=Non-Navigable;"/><UML:TaggedValue tag="ea_end" value="source"/></UML:ModelElement.taggedValue></UML:AssociationEnd><UML:AssociationEnd visibility="private" name="productOps" aggregation="none" isOrdered="false" targetScope="instance" changeable="none" isNavigable="true" type="EAID_123B8F3D_2661_4149_93CC_65EFB8861BAE"><UML:ModelElement.taggedValue><UML:TaggedValue tag="containment" value="Unspecified"/><UML:TaggedValue tag="type" value="Private"/><UML:TaggedValue tag="deststyle" value="Union=0;Derived=0;AllowDuplicates=0;Owned=0;Navigable=Navigable;"/><UML:TaggedValue tag="ea_end" value="target"/></UML:ModelElement.taggedValue></UML:AssociationEnd></UML:Association.connection></UML:Association><UML:Collaboration xmi.id="EAID_CFD82DA7_4FEB_4f43_BC11_4CC7A52F389D_Collaboration" name="Collaborations"><UML:Namespace.ownedElement><UML:ClassifierRole name="exceptions" xmi.id="EAID_57B1D7B6_0AB4_4e1d_A47D_962A01516B7B" visibility="public" base="EAID_11111111_5487_4080_A7F4_41526CB0AA00"><UML:ModelElement.taggedValue><UML:TaggedValue tag="isAbstract" value="false"/><UML:TaggedValue tag="isSpecification" value="false"/><UML:TaggedValue tag="ea_stype" value="Package"/><UML:TaggedValue tag="ea_ntype" value="0"/><UML:TaggedValue tag="version" value="1.0"/><UML:TaggedValue tag="isActive" value="false"/><UML:TaggedValue tag="package" value="EAPK_CFD82DA7_4FEB_4f43_BC11_4CC7A52F389D"/><UML:TaggedValue tag="date_created" value="2017-12-26 13:53:50"/><UML:TaggedValue tag="date_modified" value="2017-12-26 13:53:50"/><UML:TaggedValue tag="gentype" value="Java"/><UML:TaggedValue tag="tagged" value="0"/><UML:TaggedValue tag="package2" value="EAID_57B1D7B6_0AB4_4e1d_A47D_962A01516B7B"/><UML:TaggedValue tag="package_name" value="operations"/><UML:TaggedValue tag="phase" value="1.0"/><UML:TaggedValue tag="author" value="husekjos"/><UML:TaggedValue tag="complexity" value="1"/><UML:TaggedValue tag="status" value="Proposed"/><UML:TaggedValue tag="tpos" value="0"/><UML:TaggedValue tag="ea_localid" value="672"/><UML:TaggedValue tag="ea_eleType" value="package"/><UML:TaggedValue tag="style" value="BackColor=-1;BorderColor=-1;BorderWidth=-1;FontColor=-1;VSwimLanes=1;HSwimLanes=1;BorderStyle=0;"/></UML:ModelElement.taggedValue></UML:ClassifierRole></UML:Namespace.ownedElement><UML:Collaboration.interaction/></UML:Collaboration><UML:Class name="OrderInOperations" xmi.id="EAID_C771AC7B_1E55_4215_90BD_8CFF69235BA3" visibility="public" namespace="EAPK_CFD82DA7_4FEB_4f43_BC11_4CC7A52F389D" isRoot="false" isLeaf="false" isAbstract="false" isActive="false"><UML:ModelElement.taggedValue><UML:TaggedValue tag="documentation" value="Implementuje operace souvisejici s logistickymi objednavkami."/><UML:TaggedValue tag="isSpecification" value="false"/><UML:TaggedValue tag="ea_stype" value="Class"/><UML:TaggedValue tag="ea_ntype" value="0"/><UML:TaggedValue tag="version" value="1.0"/><UML:TaggedValue tag="package" value="EAPK_CFD82DA7_4FEB_4f43_BC11_4CC7A52F389D"/><UML:TaggedValue tag="date_created" value="2017-12-26 13:53:51"/><UML:TaggedValue tag="date_modified" value="2017-12-26 13:53:51"/><UML:TaggedValue tag="genfile" value="C:\Users\Pepa\Desktop\School\SI\repo\src\api\src\main\java\cz\cvut\fit\project\skld\application\operations\OrderInOperations.java"/><UML:TaggedValue tag="gentype" value="Java"/><UML:TaggedValue tag="tagged" value="0"/><UML:TaggedValue tag="package_name" value="operations"/><UML:TaggedValue tag="phase" value="1.0"/><UML:TaggedValue tag="author" value="husekjos"/><UML:TaggedValue tag="complexity" value="1"/><UML:TaggedValue tag="status" value="Proposed"/><UML:TaggedValue tag="tpos" value="0"/><UML:TaggedValue tag="ea_localid" value="4110"/><UML:TaggedValue tag="ea_eleType" value="element"/><UML:TaggedValue tag="eventflags" value="OBJ=5abb;"/><UML:TaggedValue tag="$ea_attsclassified" value="{D0588B3E-D859-4ce1-96C3-84585EEC89EE},{09748B81-44CC-4cab-A079-F45A0CD5CD2E}"/><UML:TaggedValue tag="$ea_oprparamsclassified" value="{0D5B7F77-6FF7-4353-9630-F57C0ABC237D},{097E9924-1942-46fe-AB73-1B1B165D6DB3}"/><UML:TaggedValue tag="style" value="BackColor=-1;BorderColor=-1;BorderWidth=-1;FontColor=-1;VSwimLanes=1;HSwimLanes=1;BorderStyle=0;"/></UML:ModelElement.taggedValue><UML:Classifier.feature><UML:Attribute name="movementDAO" changeable="frozen" visibility="private" ownerScope="instance" targetScope="instance"><UML:Attribute.initialValue><UML:Expression/></UML:Attribute.initialValue><UML:StructuralFeature.type><UML:Classifier xmi.idref="EAID_9555D563_A811_46c1_A4D4_836E4FC094AE"/></UML:StructuralFeature.type><UML:ModelElement.taggedValue><UML:TaggedValue tag="type" value="MovementDAO"/><UML:TaggedValue tag="derived" value="0"/><UML:TaggedValue tag="containment" value="Not Specified"/><UML:TaggedValue tag="length" value="0"/><UML:TaggedValue tag="ordered" value="0"/><UML:TaggedValue tag="collection" value="false"/><UML:TaggedValue tag="position" value="2"/><UML:TaggedValue tag="lowerBound" value="1"/><UML:TaggedValue tag="upperBound" value="1"/><UML:TaggedValue tag="duplicates" value="0"/><UML:TaggedValue tag="ea_guid" value="{A40EC615-D1A8-4ba9-8F90-67A2843FCEC2}"/><UML:TaggedValue tag="ea_localid" value="1211"/><UML:TaggedValue tag="styleex" value="volatile=0;union=0;"/></UML:ModelElement.taggedValue></UML:Attribute><UML:Attribute name="orderInDAO" changeable="frozen" visibility="private" ownerScope="instance" targetScope="instance"><UML:Attribute.initialValue><UML:Expression/></UML:Attribute.initialValue><UML:StructuralFeature.type><UML:Classifier xmi.idref="EAID_6C7AB63E_C2F8_4724_AF99_2DEFCCEEE54E"/></UML:StructuralFeature.type><UML:ModelElement.taggedValue><UML:TaggedValue tag="type" value="OrderInDAO"/><UML:TaggedValue tag="derived" value="0"/><UML:TaggedValue tag="containment" value="Not Specified"/><UML:TaggedValue tag="length" value="0"/><UML:TaggedValue tag="ordered" value="0"/><UML:TaggedValue tag="collection" value="false"/><UML:TaggedValue tag="position" value="0"/><UML:TaggedValue tag="lowerBound" value="1"/><UML:TaggedValue tag="upperBound" value="1"/><UML:TaggedValue tag="duplicates" value="0"/><UML:TaggedValue tag="ea_guid" value="{57AEB5E5-531F-48d1-8BE5-5A8C48A15D79}"/><UML:TaggedValue tag="ea_localid" value="1212"/><UML:TaggedValue tag="styleex" value="volatile=0;union=0;"/></UML:ModelElement.taggedValue></UML:Attribute><UML:Attribute name="productDAO" changeable="frozen" visibility="private" ownerScope="instance" targetScope="instance"><UML:Attribute.initialValue><UML:Expression/></UML:Attribute.initialValue><UML:StructuralFeature.type><UML:Classifier xmi.idref="EAID_5F9E8C93_59DC_42bb_8209_3611D2544AB8"/></UML:StructuralFeature.type><UML:ModelElement.taggedValue><UML:TaggedValue tag="type" value="ProductDAO"/><UML:TaggedValue tag="derived" value="0"/><UML:TaggedValue tag="containment" value="Not Specified"/><UML:TaggedValue tag="length" value="0"/><UML:TaggedValue tag="ordered" value="0"/><UML:TaggedValue tag="collection" value="false"/><UML:TaggedValue tag="position" value="1"/><UML:TaggedValue tag="lowerBound" value="1"/><UML:TaggedValue tag="upperBound" value="1"/><UML:TaggedValue tag="duplicates" value="0"/><UML:TaggedValue tag="ea_guid" value="{75F08FF9-545B-4816-982A-0513FD9206CD}"/><UML:TaggedValue tag="ea_localid" value="1213"/><UML:TaggedValue tag="styleex" value="volatile=0;union=0;"/></UML:ModelElement.taggedValue></UML:Attribute><UML:Operation name="close" visibility="public" ownerScope="instance" isQuery="false" concurrency="sequential"><UML:ModelElement.taggedValue><UML:TaggedValue tag="documentation" value="Uzavre logistickou objednavku a zada prislusna umisteni produktu do systemu podle predanych produktu z requestu"/><UML:TaggedValue tag="type" value="OrderIn"/><UML:TaggedValue tag="const" value="false"/><UML:TaggedValue tag="synchronised" value="0"/><UML:TaggedValue tag="concurrency" value="Sequential"/><UML:TaggedValue tag="position" value="3"/><UML:TaggedValue tag="returnarray" value="0"/><UML:TaggedValue tag="pure" value="0"/><UML:TaggedValue tag="ea_guid" value="{8A14C84C-AA4F-45db-A1B0-C90B5C6F7EB8}"/><UML:TaggedValue tag="ea_localid" value="2402"/><UML:TaggedValue tag="throws" value="NotFoundException,InvalidStateException" xmi.id="EAID_5E32856D_ED16_4279_B9B2_BCC05B5F836E"><XMI.extension xmi.extender="Enterprise Architect 2.5"><UML:Comment name="@exception InvalidStateException Objednavka neni ve stavu otevreno"/></XMI.extension></UML:TaggedValue></UML:ModelElement.taggedValue><UML:BehavioralFeature.parameter><UML:Parameter kind="return" visibility="public"><UML:Parameter.type><UML:Classifier xmi.idref="EAID_5586CC68_685B_4da4_962B_EA569EAD3143"/></UML:Parameter.type><UML:ModelElement.taggedValue><UML:TaggedValue tag="pos" value="0"/><UML:TaggedValue tag="type" value="OrderIn"/><UML:TaggedValue tag="const" value="0"/><UML:TaggedValue tag="classifier" value="EAID_5586CC68_685B_4da4_962B_EA569EAD3143"/><UML:TaggedValue tag="ea_guid" value="{RETURNID-AA4F-45db-A1B0-C90B5C6F7EB8}"/></UML:ModelElement.taggedValue><UML:Parameter.defaultValue><UML:Expression/></UML:Parameter.defaultValue></UML:Parameter><UML:Parameter name="handler" kind="in" visibility="public"><UML:Parameter.type><UML:Classifier xmi.idref="EAID_E971BBB6_4C2F_4889_87F4_D5837581E3DB"/></UML:Parameter.type><UML:ModelElement.taggedValue><UML:TaggedValue tag="note" value="Uzivatel, ktery operaci zadal do systemu"/><UML:TaggedValue tag="pos" value="0"/><UML:TaggedValue tag="type" value="User"/><UML:TaggedValue tag="const" value="0"/><UML:TaggedValue tag="classifier" value="EAID_E971BBB6_4C2F_4889_87F4_D5837581E3DB"/><UML:TaggedValue tag="ea_guid" value="{93BE47CB-E164-40df-8A57-26AB1DAD570B}"/></UML:ModelElement.taggedValue><UML:Parameter.defaultValue><UML:Expression/></UML:Parameter.defaultValue></UML:Parameter><UML:Parameter name="request" kind="in" visibility="public"><UML:Parameter.type><UML:Classifier xmi.idref="eaxmiid6"/></UML:Parameter.type><UML:ModelElement.taggedValue><UML:TaggedValue tag="note" value="Uzavirana logisticka objednavka"/><UML:TaggedValue tag="pos" value="1"/><UML:TaggedValue tag="type" value="OrderInRepresentation"/><UML:TaggedValue tag="const" value="0"/><UML:TaggedValue tag="ea_guid" value="{1CE17B42-C75C-4b05-9234-A2205102AC93}"/></UML:ModelElement.taggedValue><UML:Parameter.defaultValue><UML:Expression/></UML:Parameter.defaultValue></UML:Parameter></UML:BehavioralFeature.parameter></UML:Operation><UML:Operation name="create" visibility="public" ownerScope="instance" isQuery="false" concurrency="sequential"><UML:ModelElement.taggedValue><UML:TaggedValue tag="documentation" value="Vytvori novou logistickou objednavku."/><UML:TaggedValue tag="type" value="OrderIn"/><UML:TaggedValue tag="const" value="false"/><UML:TaggedValue tag="synchronised" value="0"/><UML:TaggedValue tag="concurrency" value="Sequential"/><UML:TaggedValue tag="position" value="5"/><UML:TaggedValue tag="returnarray" value="0"/><UML:TaggedValue tag="pure" value="0"/><UML:TaggedValue tag="ea_guid" value="{CF4E8A37-D407-4462-A5FC-2CACC3AE9833}"/><UML:TaggedValue tag="ea_localid" value="2403"/><UML:TaggedValue tag="throws" value="InvalidStateException" xmi.id="EAID_CBC096C9_E5B3_4fe8_AD46_2D76E49DC939"><XMI.extension xmi.extender="Enterprise Architect 2.5"><UML:Comment name="@exception InvalidStateException Logisticka objednavka se zadanym ID jiz v systemu existuje"/></XMI.extension></UML:TaggedValue></UML:ModelElement.taggedValue><UML:BehavioralFeature.parameter><UML:Parameter kind="return" visibility="public"><UML:Parameter.type><UML:Classifier xmi.idref="EAID_5586CC68_685B_4da4_962B_EA569EAD3143"/></UML:Parameter.type><UML:ModelElement.taggedValue><UML:TaggedValue tag="pos" value="0"/><UML:TaggedValue tag="type" value="OrderIn"/><UML:TaggedValue tag="const" value="0"/><UML:TaggedValue tag="classifier" value="EAID_5586CC68_685B_4da4_962B_EA569EAD3143"/><UML:TaggedValue tag="ea_guid" value="{RETURNID-D407-4462-A5FC-2CACC3AE9833}"/></UML:ModelElement.taggedValue><UML:Parameter.defaultValue><UML:Expression/></UML:Parameter.defaultValue></UML:Parameter><UML:Parameter name="creator" kind="in" visibility="public"><UML:Parameter.type><UML:Classifier xmi.idref="EAID_E971BBB6_4C2F_4889_87F4_D5837581E3DB"/></UML:Parameter.type><UML:ModelElement.taggedValue><UML:TaggedValue tag="note" value="Uzivatel, ktery operaci zadal do systemu"/><UML:TaggedValue tag="pos" value="0"/><UML:TaggedValue tag="type" value="User"/><UML:TaggedValue tag="const" value="0"/><UML:TaggedValue tag="classifier" value="EAID_E971BBB6_4C2F_4889_87F4_D5837581E3DB"/><UML:TaggedValue tag="ea_guid" value="{E8714641-13ED-4641-A59C-9706B113B5DC}"/></UML:ModelElement.taggedValue><UML:Parameter.defaultValue><UML:Expression/></UML:Parameter.defaultValue></UML:Parameter><UML:Parameter name="request" kind="in" visibility="public"><UML:Parameter.type><UML:Classifier xmi.idref="eaxmiid7"/></UML:Parameter.type><UML:ModelElement.taggedValue><UML:TaggedValue tag="pos" value="1"/><UML:TaggedValue tag="type" value="OrderInChange"/><UML:TaggedValue tag="const" value="0"/><UML:TaggedValue tag="ea_guid" value="{86FE30C3-A19F-4685-98CE-0AFC2704952C}"/></UML:ModelElement.taggedValue><UML:Parameter.defaultValue><UML:Expression/></UML:Parameter.defaultValue></UML:Parameter></UML:BehavioralFeature.parameter></UML:Operation><UML:Operation name="edit" visibility="public" ownerScope="instance" isQuery="false" concurrency="sequential"><UML:ModelElement.taggedValue><UML:TaggedValue tag="documentation" value="Upravi logistickou objednavku se zadanym ID. V soucasnosti smi byt modifikovan pouze status."/><UML:TaggedValue tag="type" value="OrderIn"/><UML:TaggedValue tag="const" value="false"/><UML:TaggedValue tag="synchronised" value="0"/><UML:TaggedValue tag="concurrency" value="Sequential"/><UML:TaggedValue tag="position" value="2"/><UML:TaggedValue tag="returnarray" value="0"/><UML:TaggedValue tag="pure" value="0"/><UML:TaggedValue tag="ea_guid" value="{7DB31714-F0BD-4155-A7D0-FAB5EE7B7635}"/><UML:TaggedValue tag="ea_localid" value="2404"/><UML:TaggedValue tag="throws" value="NotFoundException,InvalidStateException" xmi.id="EAID_F4F293CC_E037_42f6_AFE3_C3316948E5C7"><XMI.extension xmi.extender="Enterprise Architect 2.5"><UML:Comment name="@exception InvalidStateException Editovana objednavka neni ve stavu otevreno"/></XMI.extension></UML:TaggedValue></UML:ModelElement.taggedValue><UML:BehavioralFeature.parameter><UML:Parameter kind="return" visibility="public"><UML:Parameter.type><UML:Classifier xmi.idref="EAID_5586CC68_685B_4da4_962B_EA569EAD3143"/></UML:Parameter.type><UML:ModelElement.taggedValue><UML:TaggedValue tag="pos" value="0"/><UML:TaggedValue tag="type" value="OrderIn"/><UML:TaggedValue tag="const" value="0"/><UML:TaggedValue tag="classifier" value="EAID_5586CC68_685B_4da4_962B_EA569EAD3143"/><UML:TaggedValue tag="ea_guid" value="{RETURNID-F0BD-4155-A7D0-FAB5EE7B7635}"/></UML:ModelElement.taggedValue><UML:Parameter.defaultValue><UML:Expression/></UML:Parameter.defaultValue></UML:Parameter><UML:Parameter name="change" kind="in" visibility="public"><UML:Parameter.type><UML:Classifier xmi.idref="eaxmiid7"/></UML:Parameter.type><UML:ModelElement.taggedValue><UML:TaggedValue tag="pos" value="0"/><UML:TaggedValue tag="type" value="OrderInChange"/><UML:TaggedValue tag="const" value="0"/><UML:TaggedValue tag="ea_guid" value="{0E22A8EC-EA83-4695-B5C7-3E8628AECA8E}"/></UML:ModelElement.taggedValue><UML:Parameter.defaultValue><UML:Expression/></UML:Parameter.defaultValue></UML:Parameter></UML:BehavioralFeature.parameter></UML:Operation><UML:Operation name="get" visibility="public" ownerScope="instance" isQuery="false" concurrency="sequential"><UML:ModelElement.taggedValue><UML:TaggedValue tag="documentation" value="Vraci logistickou objednavku podle zadaneho ID."/><UML:TaggedValue tag="type" value="OrderIn"/><UML:TaggedValue tag="const" value="false"/><UML:TaggedValue tag="synchronised" value="0"/><UML:TaggedValue tag="concurrency" value="Sequential"/><UML:TaggedValue tag="position" value="1"/><UML:TaggedValue tag="returnarray" value="0"/><UML:TaggedValue tag="pure" value="0"/><UML:TaggedValue tag="ea_guid" value="{279BC559-4298-4cf4-9E67-7DABD8F4A916}"/><UML:TaggedValue tag="ea_localid" value="2405"/><UML:TaggedValue tag="throws" value="NotFoundException" xmi.id="EAID_63288B29_C2B7_464e_AC14_0EC02460AB96"/></UML:ModelElement.taggedValue><UML:BehavioralFeature.parameter><UML:Parameter kind="return" visibility="public"><UML:Parameter.type><UML:Classifier xmi.idref="EAID_5586CC68_685B_4da4_962B_EA569EAD3143"/></UML:Parameter.type><UML:ModelElement.taggedValue><UML:TaggedValue tag="pos" value="0"/><UML:TaggedValue tag="type" value="OrderIn"/><UML:TaggedValue tag="const" value="0"/><UML:TaggedValue tag="classifier" value="EAID_5586CC68_685B_4da4_962B_EA569EAD3143"/><UML:TaggedValue tag="ea_guid" value="{RETURNID-4298-4cf4-9E67-7DABD8F4A916}"/></UML:ModelElement.taggedValue><UML:Parameter.defaultValue><UML:Expression/></UML:Parameter.defaultValue></UML:Parameter><UML:Parameter name="id" kind="in" visibility="public"><UML:Parameter.type><UML:Classifier xmi.idref="eaxmiid2"/></UML:Parameter.type><UML:ModelElement.taggedValue><UML:TaggedValue tag="note" value="ID"/><UML:TaggedValue tag="pos" value="0"/><UML:TaggedValue tag="type" value="long"/><UML:TaggedValue tag="const" value="0"/><UML:TaggedValue tag="ea_guid" value="{678582F9-D6B0-4ab5-8ED3-5B76DEB5588C}"/></UML:ModelElement.taggedValue><UML:Parameter.defaultValue><UML:Expression/></UML:Parameter.defaultValue></UML:Parameter></UML:BehavioralFeature.parameter></UML:Operation><UML:Operation name="getAll" visibility="public" ownerScope="instance" isQuery="false" concurrency="sequential"><UML:ModelElement.taggedValue><UML:TaggedValue tag="documentation" value="Vraci seznam vsech logistickych objednavek z databaze.&#xA;@return Seznam logistickych objednavek"/><UML:TaggedValue tag="type" value="List&lt;OrderIn&gt;"/><UML:TaggedValue tag="const" value="false"/><UML:TaggedValue tag="synchronised" value="0"/><UML:TaggedValue tag="concurrency" value="Sequential"/><UML:TaggedValue tag="position" value="6"/><UML:TaggedValue tag="returnarray" value="0"/><UML:TaggedValue tag="pure" value="0"/><UML:TaggedValue tag="ea_guid" value="{1A5DE891-BFA2-4b8b-A80C-5444D7F66D71}"/><UML:TaggedValue tag="ea_localid" value="2406"/></UML:ModelElement.taggedValue><UML:BehavioralFeature.parameter><UML:Parameter kind="return" visibility="public"><UML:Parameter.type><UML:Classifier xmi.idref="eaxmiid8"/></UML:Parameter.type><UML:ModelElement.taggedValue><UML:TaggedValue tag="pos" value="0"/><UML:TaggedValue tag="type" value="List&lt;OrderIn&gt;"/><UML:TaggedValue tag="const" value="0"/><UML:TaggedValue tag="ea_guid" value="{RETURNID-BFA2-4b8b-A80C-5444D7F66D71}"/></UML:ModelElement.taggedValue><UML:Parameter.defaultValue><UML:Expression/></UML:Parameter.defaultValue></UML:Parameter></UML:BehavioralFeature.parameter></UML:Operation><UML:Operation name="OrderInOperations" visibility="public" ownerScope="instance" isQuery="false" concurrency="sequential"><UML:ModelElement.taggedValue><UML:TaggedValue tag="documentation" value="Konstruktor."/><UML:TaggedValue tag="const" value="false"/><UML:TaggedValue tag="synchronised" value="0"/><UML:TaggedValue tag="concurrency" value="Sequential"/><UML:TaggedValue tag="position" value="0"/><UML:TaggedValue tag="returnarray" value="0"/><UML:TaggedValue tag="pure" value="0"/><UML:TaggedValue tag="ea_guid" value="{9A6C998C-B02F-41d5-BC76-BFAC6332ED02}"/><UML:TaggedValue tag="ea_localid" value="2407"/></UML:ModelElement.taggedValue><UML:BehavioralFeature.parameter><UML:Parameter kind="return" visibility="public"><UML:Parameter.type><UML:Classifier xmi.idref="eaxmiid5"/></UML:Parameter.type><UML:ModelElement.taggedValue><UML:TaggedValue tag="pos" value="0"/><UML:TaggedValue tag="const" value="0"/><UML:TaggedValue tag="ea_guid" value="{RETURNID-B02F-41d5-BC76-BFAC6332ED02}"/></UML:ModelElement.taggedValue><UML:Parameter.defaultValue><UML:Expression/></UML:Parameter.defaultValue></UML:Parameter><UML:Parameter name="orderInDAO" kind="in" visibility="public"><UML:Parameter.type><UML:Classifier xmi.idref="EAID_6C7AB63E_C2F8_4724_AF99_2DEFCCEEE54E"/></UML:Parameter.type><UML:ModelElement.taggedValue><UML:TaggedValue tag="note" value="DAO pro pristup k logistickym objednavkam"/><UML:TaggedValue tag="pos" value="0"/><UML:TaggedValue tag="type" value="OrderInDAO"/><UML:TaggedValue tag="const" value="0"/><UML:TaggedValue tag="classifier" value="EAID_6C7AB63E_C2F8_4724_AF99_2DEFCCEEE54E"/><UML:TaggedValue tag="ea_guid" value="{03E9A8E7-7A97-4f01-BDB5-5159A569D853}"/></UML:ModelElement.taggedValue><UML:Parameter.defaultValue><UML:Expression/></UML:Parameter.defaultValue></UML:Parameter><UML:Parameter name="productDAO" kind="in" visibility="public"><UML:Parameter.type><UML:Classifier xmi.idref="EAID_5F9E8C93_59DC_42bb_8209_3611D2544AB8"/></UML:Parameter.type><UML:ModelElement.taggedValue><UML:TaggedValue tag="note" value="DAO pro pristup k produktum"/><UML:TaggedValue tag="pos" value="1"/><UML:TaggedValue tag="type" value="ProductDAO"/><UML:TaggedValue tag="const" value="0"/><UML:TaggedValue tag="classifier" value="EAID_5F9E8C93_59DC_42bb_8209_3611D2544AB8"/><UML:TaggedValue tag="ea_guid" value="{E4B410AD-14C5-4e12-A722-B5C536135E5E}"/></UML:ModelElement.taggedValue><UML:Parameter.defaultValue><UML:Expression/></UML:Parameter.defaultValue></UML:Parameter><UML:Parameter name="movementDAO" kind="in" visibility="public"><UML:Parameter.type><UML:Classifier xmi.idref="EAID_9555D563_A811_46c1_A4D4_836E4FC094AE"/></UML:Parameter.type><UML:ModelElement.taggedValue><UML:TaggedValue tag="note" value="DAO pro pristup k umistenim produktu"/><UML:TaggedValue tag="pos" value="2"/><UML:TaggedValue tag="type" value="MovementDAO"/><UML:TaggedValue tag="const" value="0"/><UML:TaggedValue tag="classifier" value="EAID_9555D563_A811_46c1_A4D4_836E4FC094AE"/><UML:TaggedValue tag="ea_guid" value="{A0DAEB8B-102D-4356-A34A-77BC7C272603}"/></UML:ModelElement.taggedValue><UML:Parameter.defaultValue><UML:Expression/></UML:Parameter.defaultValue></UML:Parameter></UML:BehavioralFeature.parameter></UML:Operation><UML:Operation name="refuse" visibility="public" ownerScope="instance" isQuery="false" concurrency="sequential"><UML:ModelElement.taggedValue><UML:TaggedValue tag="documentation" value="Zamitne logistickou objednavku."/><UML:TaggedValue tag="type" value="OrderIn"/><UML:TaggedValue tag="const" value="false"/><UML:TaggedValue tag="synchronised" value="0"/><UML:TaggedValue tag="concurrency" value="Sequential"/><UML:TaggedValue tag="position" value="4"/><UML:TaggedValue tag="returnarray" value="0"/><UML:TaggedValue tag="pure" value="0"/><UML:TaggedValue tag="ea_guid" value="{BDDB3050-3F37-48e1-9F5B-7D7F5B663632}"/><UML:TaggedValue tag="ea_localid" value="2408"/><UML:TaggedValue tag="throws" value="NotFoundException,InvalidStateException" xmi.id="EAID_DDA58240_95D6_4daf_A87C_3FF9BD2AD18F"><XMI.extension xmi.extender="Enterprise Architect 2.5"><UML:Comment name="@exception InvalidStateException Objednavka neni ve stavu otevreno"/></XMI.extension></UML:TaggedValue></UML:ModelElement.taggedValue><UML:BehavioralFeature.parameter><UML:Parameter kind="return" visibility="public"><UML:Parameter.type><UML:Classifier xmi.idref="EAID_5586CC68_685B_4da4_962B_EA569EAD3143"/></UML:Parameter.type><UML:ModelElement.taggedValue><UML:TaggedValue tag="pos" value="0"/><UML:TaggedValue tag="type" value="OrderIn"/><UML:TaggedValue tag="const" value="0"/><UML:TaggedValue tag="classifier" value="EAID_5586CC68_685B_4da4_962B_EA569EAD3143"/><UML:TaggedValue tag="ea_guid" value="{RETURNID-3F37-48e1-9F5B-7D7F5B663632}"/></UML:ModelElement.taggedValue><UML:Parameter.defaultValue><UML:Expression/></UML:Parameter.defaultValue></UML:Parameter><UML:Parameter name="handler" kind="in" visibility="public"><UML:Parameter.type><UML:Classifier xmi.idref="EAID_E971BBB6_4C2F_4889_87F4_D5837581E3DB"/></UML:Parameter.type><UML:ModelElement.taggedValue><UML:TaggedValue tag="note" value="Uzivatel, ktery operaci zadal do systemu"/><UML:TaggedValue tag="pos" value="0"/><UML:TaggedValue tag="type" value="User"/><UML:TaggedValue tag="const" value="0"/><UML:TaggedValue tag="classifier" value="EAID_E971BBB6_4C2F_4889_87F4_D5837581E3DB"/><UML:TaggedValue tag="ea_guid" value="{72306834-4F02-4a78-BB2D-0AF23E85C4C6}"/></UML:ModelElement.taggedValue><UML:Parameter.defaultValue><UML:Expression/></UML:Parameter.defaultValue></UML:Parameter><UML:Parameter name="id" kind="in" visibility="public"><UML:Parameter.type><UML:Classifier xmi.idref="eaxmiid2"/></UML:Parameter.type><UML:ModelElement.taggedValue><UML:TaggedValue tag="note" value="ID zamitane logisticke objednavky"/><UML:TaggedValue tag="pos" value="1"/><UML:TaggedValue tag="type" value="long"/><UML:TaggedValue tag="const" value="0"/><UML:TaggedValue tag="ea_guid" value="{2B4C48A5-72E9-4847-89A0-2316243F7782}"/></UML:ModelElement.taggedValue><UML:Parameter.defaultValue><UML:Expression/></UML:Parameter.defaultValue></UML:Parameter></UML:BehavioralFeature.parameter></UML:Operation><UML:Operation name="sumMapKeys" visibility="private" ownerScope="instance" isQuery="false" concurrency="sequential"><UML:ModelElement.taggedValue><UML:TaggedValue tag="type" value="long"/><UML:TaggedValue tag="const" value="false"/><UML:TaggedValue tag="synchronised" value="0"/><UML:TaggedValue tag="concurrency" value="Sequential"/><UML:TaggedValue tag="position" value="7"/><UML:TaggedValue tag="returnarray" value="0"/><UML:TaggedValue tag="pure" value="0"/><UML:TaggedValue tag="ea_guid" value="{EFF286B7-C923-4d6a-A86B-CD26D89AAD1A}"/><UML:TaggedValue tag="ea_localid" value="2409"/></UML:ModelElement.taggedValue><UML:BehavioralFeature.parameter><UML:Parameter kind="return" visibility="public"><UML:Parameter.type><UML:Classifier xmi.idref="eaxmiid2"/></UML:Parameter.type><UML:ModelElement.taggedValue><UML:TaggedValue tag="pos" value="0"/><UML:TaggedValue tag="type" value="long"/><UML:TaggedValue tag="const" value="0"/><UML:TaggedValue tag="ea_guid" value="{RETURNID-C923-4d6a-A86B-CD26D89AAD1A}"/></UML:ModelElement.taggedValue><UML:Parameter.defaultValue><UML:Expression/></UML:Parameter.defaultValue></UML:Parameter><UML:Parameter name="m" kind="in" visibility="public"><UML:Parameter.type><UML:Classifier xmi.idref="eaxmiid9"/></UML:Parameter.type><UML:ModelElement.taggedValue><UML:TaggedValue tag="pos" value="0"/><UML:TaggedValue tag="type" value="Map&lt;String, Long&gt;"/><UML:TaggedValue tag="const" value="0"/><UML:TaggedValue tag="ea_guid" value="{2A24077B-ADBE-463f-A397-0F23DF52FFD0}"/></UML:ModelElement.taggedValue><UML:Parameter.defaultValue><UML:Expression/></UML:Parameter.defaultValue></UML:Parameter></UML:BehavioralFeature.parameter></UML:Operation></UML:Classifier.feature></UML:Class><UML:Association xmi.id="EAID_01D06617_2498_4a0b_B321_114816EE43FC" visibility="public" isRoot="false" isLeaf="false" isAbstract="false"><UML:ModelElement.taggedValue><UML:TaggedValue tag="style" value="3"/><UML:TaggedValue tag="ea_type" value="Association"/><UML:TaggedValue tag="direction" value="Source -&gt; Destination"/><UML:TaggedValue tag="linemode" value="3"/><UML:TaggedValue tag="linecolor" value="-1"/><UML:TaggedValue tag="linewidth" value="0"/><UML:TaggedValue tag="seqno" value="0"/><UML:TaggedValue tag="headStyle" value="0"/><UML:TaggedValue tag="lineStyle" value="0"/><UML:TaggedValue tag="ea_localid" value="2768"/><UML:TaggedValue tag="ea_sourceName" value="OrderInOperations"/><UML:TaggedValue tag="ea_targetName" value="MovementDAO"/><UML:TaggedValue tag="ea_sourceType" value="Class"/><UML:TaggedValue tag="ea_targetType" value="Interface"/><UML:TaggedValue tag="ea_sourceID" value="4110"/><UML:TaggedValue tag="ea_targetID" value="4099"/><UML:TaggedValue tag="virtualInheritance" value="0"/><UML:TaggedValue tag="rt" value="-movementDAO"/></UML:ModelElement.taggedValue><UML:Association.connection><UML:AssociationEnd visibility="public" aggregation="none" isOrdered="false" targetScope="instance" changeable="none" isNavigable="false" type="EAID_C771AC7B_1E55_4215_90BD_8CFF69235BA3"><UML:ModelElement.taggedValue><UML:TaggedValue tag="containment" value="Unspecified"/><UML:TaggedValue tag="sourcestyle" value="Union=0;Derived=0;AllowDuplicates=0;Owned=0;Navigable=Non-Navigable;"/><UML:TaggedValue tag="ea_end" value="source"/></UML:ModelElement.taggedValue></UML:AssociationEnd><UML:AssociationEnd visibility="private" name="movementDAO" aggregation="none" isOrdered="false" targetScope="instance" changeable="none" isNavigable="true" type="EAID_9555D563_A811_46c1_A4D4_836E4FC094AE"><UML:ModelElement.taggedValue><UML:TaggedValue tag="containment" value="Unspecified"/><UML:TaggedValue tag="type" value="Private"/><UML:TaggedValue tag="deststyle" value="Union=0;Derived=0;AllowDuplicates=0;Owned=0;Navigable=Navigable;"/><UML:TaggedValue tag="ea_end" value="target"/></UML:ModelElement.taggedValue></UML:AssociationEnd></UML:Association.connection></UML:Association><UML:Association xmi.id="EAID_0B1FE562_2C4C_4de6_B59A_33593C564459" visibility="public" isRoot="false" isLeaf="false" isAbstract="false"><UML:ModelElement.taggedValue><UML:TaggedValue tag="style" value="3"/><UML:TaggedValue tag="ea_type" value="Association"/><UML:TaggedValue tag="direction" value="Source -&gt; Destination"/><UML:TaggedValue tag="linemode" value="3"/><UML:TaggedValue tag="linecolor" value="-1"/><UML:TaggedValue tag="linewidth" value="0"/><UML:TaggedValue tag="seqno" value="0"/><UML:TaggedValue tag="headStyle" value="0"/><UML:TaggedValue tag="lineStyle" value="0"/><UML:TaggedValue tag="ea_localid" value="2769"/><UML:TaggedValue tag="ea_sourceName" value="OrderInOperations"/><UML:TaggedValue tag="ea_targetName" value="OrderInDAO"/><UML:TaggedValue tag="ea_sourceType" value="Class"/><UML:TaggedValue tag="ea_targetType" value="Interface"/><UML:TaggedValue tag="ea_sourceID" value="4110"/><UML:TaggedValue tag="ea_targetID" value="4100"/><UML:TaggedValue tag="virtualInheritance" value="0"/><UML:TaggedValue tag="rt" value="-orderInDAO"/></UML:ModelElement.taggedValue><UML:Association.connection><UML:AssociationEnd visibility="public" aggregation="none" isOrdered="false" targetScope="instance" changeable="none" isNavigable="false" type="EAID_C771AC7B_1E55_4215_90BD_8CFF69235BA3"><UML:ModelElement.taggedValue><UML:TaggedValue tag="containment" value="Unspecified"/><UML:TaggedValue tag="sourcestyle" value="Union=0;Derived=0;AllowDuplicates=0;Owned=0;Navigable=Non-Navigable;"/><UML:TaggedValue tag="ea_end" value="source"/></UML:ModelElement.taggedValue></UML:AssociationEnd><UML:AssociationEnd visibility="private" name="orderInDAO" aggregation="none" isOrdered="false" targetScope="instance" changeable="none" isNavigable="true" type="EAID_6C7AB63E_C2F8_4724_AF99_2DEFCCEEE54E"><UML:ModelElement.taggedValue><UML:TaggedValue tag="containment" value="Unspecified"/><UML:TaggedValue tag="type" value="Private"/><UML:TaggedValue tag="deststyle" value="Union=0;Derived=0;AllowDuplicates=0;Owned=0;Navigable=Navigable;"/><UML:TaggedValue tag="ea_end" value="target"/></UML:ModelElement.taggedValue></UML:AssociationEnd></UML:Association.connection></UML:Association><UML:Association xmi.id="EAID_AD0DFBD0_CFA7_4c28_907F_549BECA4AEDC" visibility="public" isRoot="false" isLeaf="false" isAbstract="false"><UML:ModelElement.taggedValue><UML:TaggedValue tag="style" value="3"/><UML:TaggedValue tag="ea_type" value="Association"/><UML:TaggedValue tag="direction" value="Source -&gt; Destination"/><UML:TaggedValue tag="linemode" value="3"/><UML:TaggedValue tag="linecolor" value="-1"/><UML:TaggedValue tag="linewidth" value="0"/><UML:TaggedValue tag="seqno" value="0"/><UML:TaggedValue tag="headStyle" value="0"/><UML:TaggedValue tag="lineStyle" value="0"/><UML:TaggedValue tag="ea_localid" value="2775"/><UML:TaggedValue tag="ea_sourceName" value="OrderInsResource"/><UML:TaggedValue tag="ea_targetName" value="OrderInOperations"/><UML:TaggedValue tag="ea_sourceType" value="Class"/><UML:TaggedValue tag="ea_targetType" value="Class"/><UML:TaggedValue tag="ea_sourceID" value="4115"/><UML:TaggedValue tag="ea_targetID" value="4110"/><UML:TaggedValue tag="virtualInheritance" value="0"/><UML:TaggedValue tag="rt" value="-orderInOps"/></UML:ModelElement.taggedValue><UML:Association.connection><UML:AssociationEnd visibility="public" aggregation="none" isOrdered="false" targetScope="instance" changeable="none" isNavigable="false" type="EAID_7A147E0A_C6B9_4037_AC76_E08AFCCA83CA"><UML:ModelElement.taggedValue><UML:TaggedValue tag="containment" value="Unspecified"/><UML:TaggedValue tag="sourcestyle" value="Union=0;Derived=0;AllowDuplicates=0;Owned=0;Navigable=Non-Navigable;"/><UML:TaggedValue tag="ea_end" value="source"/></UML:ModelElement.taggedValue></UML:AssociationEnd><UML:AssociationEnd visibility="private" name="orderInOps" aggregation="none" isOrdered="false" targetScope="instance" changeable="none" isNavigable="true" type="EAID_C771AC7B_1E55_4215_90BD_8CFF69235BA3"><UML:ModelElement.taggedValue><UML:TaggedValue tag="containment" value="Unspecified"/><UML:TaggedValue tag="type" value="Private"/><UML:TaggedValue tag="deststyle" value="Union=0;Derived=0;AllowDuplicates=0;Owned=0;Navigable=Navigable;"/><UML:TaggedValue tag="ea_end" value="target"/></UML:ModelElement.taggedValue></UML:AssociationEnd></UML:Association.connection></UML:Association><UML:Association xmi.id="EAID_AEF8C612_AE14_40df_BB1C_B391F55C6E6A" visibility="public" isRoot="false" isLeaf="false" isAbstract="false"><UML:ModelElement.taggedValue><UML:TaggedValue tag="style" value="3"/><UML:TaggedValue tag="ea_type" value="Association"/><UML:TaggedValue tag="direction" value="Source -&gt; Destination"/><UML:TaggedValue tag="linemode" value="3"/><UML:TaggedValue tag="linecolor" value="-1"/><UML:TaggedValue tag="linewidth" value="0"/><UML:TaggedValue tag="seqno" value="0"/><UML:TaggedValue tag="headStyle" value="0"/><UML:TaggedValue tag="lineStyle" value="0"/><UML:TaggedValue tag="ea_localid" value="2770"/><UML:TaggedValue tag="ea_sourceName" value="OrderInOperations"/><UML:TaggedValue tag="ea_targetName" value="ProductDAO"/><UML:TaggedValue tag="ea_sourceType" value="Class"/><UML:TaggedValue tag="ea_targetType" value="Interface"/><UML:TaggedValue tag="ea_sourceID" value="4110"/><UML:TaggedValue tag="ea_targetID" value="4102"/><UML:TaggedValue tag="virtualInheritance" value="0"/><UML:TaggedValue tag="rt" value="-productDAO"/></UML:ModelElement.taggedValue><UML:Association.connection><UML:AssociationEnd visibility="public" aggregation="none" isOrdered="false" targetScope="instance" changeable="none" isNavigable="false" type="EAID_C771AC7B_1E55_4215_90BD_8CFF69235BA3"><UML:ModelElement.taggedValue><UML:TaggedValue tag="containment" value="Unspecified"/><UML:TaggedValue tag="sourcestyle" value="Union=0;Derived=0;AllowDuplicates=0;Owned=0;Navigable=Non-Navigable;"/><UML:TaggedValue tag="ea_end" value="source"/></UML:ModelElement.taggedValue></UML:AssociationEnd><UML:AssociationEnd visibility="private" name="productDAO" aggregation="none" isOrdered="false" targetScope="instance" changeable="none" isNavigable="true" type="EAID_5F9E8C93_59DC_42bb_8209_3611D2544AB8"><UML:ModelElement.taggedValue><UML:TaggedValue tag="containment" value="Unspecified"/><UML:TaggedValue tag="type" value="Private"/><UML:TaggedValue tag="deststyle" value="Union=0;Derived=0;AllowDuplicates=0;Owned=0;Navigable=Navigable;"/><UML:TaggedValue tag="ea_end" value="target"/></UML:ModelElement.taggedValue></UML:AssociationEnd></UML:Association.connection></UML:Association><UML:Association xmi.id="EAID_E03A480A_1597_43fd_A85F_A5073A0B4967" visibility="public" isRoot="false" isLeaf="false" isAbstract="false"><UML:ModelElement.taggedValue><UML:TaggedValue tag="style" value="3"/><UML:TaggedValue tag="ea_type" value="Association"/><UML:TaggedValue tag="direction" value="Source -&gt; Destination"/><UML:TaggedValue tag="linemode" value="3"/><UML:TaggedValue tag="linecolor" value="-1"/><UML:TaggedValue tag="linewidth" value="0"/><UML:TaggedValue tag="seqno" value="0"/><UML:TaggedValue tag="headStyle" value="0"/><UML:TaggedValue tag="lineStyle" value="0"/><UML:TaggedValue tag="ea_localid" value="2774"/><UML:TaggedValue tag="ea_sourceName" value="OrderInResource"/><UML:TaggedValue tag="ea_targetName" value="OrderInOperations"/><UML:TaggedValue tag="ea_sourceType" value="Class"/><UML:TaggedValue tag="ea_targetType" value="Class"/><UML:TaggedValue tag="ea_sourceID" value="4114"/><UML:TaggedValue tag="ea_targetID" value="4110"/><UML:TaggedValue tag="virtualInheritance" value="0"/><UML:TaggedValue tag="rt" value="-orderInOps"/></UML:ModelElement.taggedValue><UML:Association.connection><UML:AssociationEnd visibility="public" aggregation="none" isOrdered="false" targetScope="instance" changeable="none" isNavigable="false" type="EAID_6E65998C_64E7_4d93_943D_0D48CCC716F2"><UML:ModelElement.taggedValue><UML:TaggedValue tag="containment" value="Unspecified"/><UML:TaggedValue tag="sourcestyle" value="Union=0;Derived=0;AllowDuplicates=0;Owned=0;Navigable=Non-Navigable;"/><UML:TaggedValue tag="ea_end" value="source"/></UML:ModelElement.taggedValue></UML:AssociationEnd><UML:AssociationEnd visibility="private" name="orderInOps" aggregation="none" isOrdered="false" targetScope="instance" changeable="none" isNavigable="true" type="EAID_C771AC7B_1E55_4215_90BD_8CFF69235BA3"><UML:ModelElement.taggedValue><UML:TaggedValue tag="containment" value="Unspecified"/><UML:TaggedValue tag="type" value="Private"/><UML:TaggedValue tag="deststyle" value="Union=0;Derived=0;AllowDuplicates=0;Owned=0;Navigable=Navigable;"/><UML:TaggedValue tag="ea_end" value="target"/></UML:ModelElement.taggedValue></UML:AssociationEnd></UML:Association.connection></UML:Association><UML:Package name="exceptions" xmi.id="EAPK_57B1D7B6_0AB4_4e1d_A47D_962A01516B7B" isRoot="false" isLeaf="false" isAbstract="false" visibility="public"><UML:ModelElement.taggedValue><UML:TaggedValue tag="parent" value="EAPK_CFD82DA7_4FEB_4f43_BC11_4CC7A52F389D"/><UML:TaggedValue tag="created" value="2017-12-26 13:53:50"/><UML:TaggedValue tag="modified" value="2017-12-26 13:53:50"/><UML:TaggedValue tag="iscontrolled" value="TRUE"/><UML:TaggedValue tag="xmlpath" value="ea9\962A01516B7B.xml"/><UML:TaggedValue tag="version" value="1.0"/><UML:TaggedValue tag="isprotected" value="FALSE"/><UML:TaggedValue tag="usedtd" value="FALSE"/><UML:TaggedValue tag="logxml" value="FALSE"/><UML:TaggedValue tag="packageFlags" value="VCCFG=SKLD;"/><UML:TaggedValue tag="savedasstub" value="true"/><UML:TaggedValue tag="phase" value="1.0"/><UML:TaggedValue tag="status" value="Proposed"/><UML:TaggedValue tag="author" value="husekjos"/><UML:TaggedValue tag="complexity" value="1"/><UML:TaggedValue tag="ea_stype" value="Public"/></UML:ModelElement.taggedValue></UML:Package></UML:Namespace.ownedElement></UML:Package><UML:DataType xmi.id="eaxmiid5" visibility="private" isRoot="false" isLeaf="false" isAbstract="false"/><UML:DataType xmi.id="eaxmiid4" name="List&lt;ProductPosition&gt;" visibility="private" isRoot="false" isLeaf="false" isAbstract="false"/><UML:DataType xmi.id="eaxmiid9" name="Map&lt;String, Long&gt;" visibility="private" isRoot="false" isLeaf="false" isAbstract="false"/><UML:DataType xmi.id="eaxmiid8" name="List&lt;OrderIn&gt;" visibility="private" isRoot="false" isLeaf="false" isAbstract="false"/><UML:DataType xmi.id="eaxmiid3" name="List&lt;Product&gt;" visibility="private" isRoot="false" isLeaf="false" isAbstract="false"/><UML:DataType xmi.id="eaxmiid7" name="OrderInChange" visibility="private" isRoot="false" isLeaf="false" isAbstract="false"/><UML:DataType xmi.id="eaxmiid1" name="ProductChange" visibility="private" isRoot="false" isLeaf="false" isAbstract="false"/><UML:DataType xmi.id="eaxmiid6" name="OrderInRepresentation" visibility="private" isRoot="false" isLeaf="false" isAbstract="false"/><UML:DataType xmi.id="eaxmiid2" name="long" visibility="private" isRoot="false" isLeaf="false" isAbstract="false"/><UML:DataType xmi.id="eaxmiid0" name="Logger" visibility="private" isRoot="false" isLeaf="false" isAbstract="false"/></UML:Namespace.ownedElement></UML:Model><UML:Diagram name="operations" xmi.id="EAID_02C9E389_AAAE_48ed_A4FF_0F9563B81603" diagramType="ClassDiagram" owner="EAPK_CFD82DA7_4FEB_4f43_BC11_4CC7A52F389D" toolName="Enterprise Architect 2.5"><UML:ModelElement.taggedValue><UML:TaggedValue tag="version" value="1.0"/><UML:TaggedValue tag="author" value="husekjos"/><UML:TaggedValue tag="created_date" value="2017-12-26 13:53:51"/><UML:TaggedValue tag="modified_date" value="2017-12-26 14:56:13"/><UML:TaggedValue tag="package" value="EAPK_CFD82DA7_4FEB_4f43_BC11_4CC7A52F389D"/><UML:TaggedValue tag="type" value="Logical"/><UML:TaggedValue tag="swimlanes" value="locked=false;orientation=0;width=0;inbar=false;names=false;color=-1;bold=false;fcol=0;tcol=-1;ofCol=-1;ufCol=-1;hl=0;ufh=0;cls=0;SwimlaneFont=lfh:-13,lfw:0,lfi:0,lfu:0,lfs:0,lfface:Calibri,lfe:0,lfo:0,lfchar:1,lfop:0,lfcp:0,lfq:0,lfpf=0,lfWidth=0;"/><UML:TaggedValue tag="matrixitems" value="locked=false;matrixactive=false;swimlanesactive=true;kanbanactive=false;width=1;clrLine=0;"/><UML:TaggedValue tag="ea_localid" value="509"/><UML:TaggedValue tag="EAStyle" value="ShowPrivate=1;ShowProtected=0;ShowPublic=0;HideRelationships=0;Locked=0;Border=1;HighlightForeign=1;PackageContents=1;SequenceNotes=0;ScalePrintImage=0;PPgs.cx=1;PPgs.cy=1;DocSize.cx=827;DocSize.cy=1169;ShowDetails=0;Orientation=P;Zoom=100;ShowTags=0;OpParams=0;VisibleAttributeDetail=0;ShowOpRetType=1;ShowIcons=1;CollabNums=0;HideProps=1;ShowReqs=0;ShowCons=0;PaperSize=9;HideParents=0;UseAlias=0;HideAtts=0;HideOps=0;HideStereo=0;HideElemStereo=0;ShowTests=0;ShowMaint=0;ConnectorNotation=UML 2.1;ExplicitNavigability=0;ShowShape=1;AdvancedElementProps=1;AdvancedFeatureProps=1;AdvancedConnectorProps=1;m_bElementClassifier=1;ShowNotes=0;SuppressBrackets=0;SuppConnectorLabels=0;PrintPageHeadFoot=0;ShowAsList=0;"/><UML:TaggedValue tag="styleex" value="SaveTag=3371B6AB;ExcludeRTF=0;DocAll=0;HideQuals=0;AttPkg=1;ShowTests=0;ShowMaint=0;SuppressFOC=1;MatrixActive=0;SwimlanesActive=1;KanbanActive=0;MatrixLineWidth=1;MatrixLineClr=0;MatrixLocked=0;TConnectorNotation=UML 2.1;TExplicitNavigability=0;AdvancedElementProps=1;AdvancedFeatureProps=1;AdvancedConnectorProps=1;m_bElementClassifier=1;ProfileData=;MDGDgm=;STBLDgm=;ShowNotes=0;VisibleAttributeDetail=0;ShowOpRetType=1;SuppressBrackets=0;SuppConnectorLabels=0;PrintPageHeadFoot=0;ShowAsList=0;SuppressedCompartments=;Theme=:119;"/></UML:ModelElement.taggedValue><UML:Diagram.element><UML:DiagramElement geometry="Left=244;Top=20;Right=486;Bottom=90;" subject="EAID_123B8F3D_2661_4149_93CC_65EFB8861BAE" seqno="1" style="DUID=903A94AB;"/><UML:DiagramElement geometry="Left=20;Top=20;Right=224;Bottom=116;" subject="EAID_C771AC7B_1E55_4215_90BD_8CFF69235BA3" seqno="2" style="DUID=ECF504F6;"/></UML:Diagram.element></UML:Diagram><UML:DiagramElement geometry="Left=470;Top=264;Right=600;Bottom=344;" subject="EAID_CFD82DA7_4FEB_4f43_BC11_4CC7A52F389D" seqno="4" style=" DUID=D4474B1D;NSL=0;BCol=-1;BFol=-1;LCol=-1;LWth=-1;fontsz=0;bold=0;black=0;italic=0;ul=0;charset=0;pitch=0;"><UML:ModelElement.taggedValue><UML:TaggedValue tag="diagram_guid" value="EAID_CE24B76B_D0E0_46ca_9A9C_ACAC0815BED6"/></UML:ModelElement.taggedValue></UML:DiagramElement></XMI.content><XMI.difference/><XMI.extensions xmi.extender="Enterprise Architect 2.5"><EAStub xmi.id="EAID_201D76DC_417E_47f1_B8F2_53871408F064" name="ProductResource" UMLType="Class"/><EAModel.paramSub/><EAStub xmi.id="EAID_E860FEA8_FD81_45b6_87EC_8D23F214484B" name="PositionDAO" UMLType="Interface"/><EAStub xmi.id="EAID_5F9E8C93_59DC_42bb_8209_3611D2544AB8" name="ProductDAO" UMLType="Interface"/><EAStub xmi.id="EAID_FF35AD95_8EE4_4877_BCC0_870E6D72A614" name="ProductsResource" UMLType="Class"/><EAStub xmi.id="EAID_9555D563_A811_46c1_A4D4_836E4FC094AE" name="MovementDAO" UMLType="Interface"/><EAStub xmi.id="EAID_6C7AB63E_C2F8_4724_AF99_2DEFCCEEE54E" name="OrderInDAO" UMLType="Interface"/><EAStub xmi.id="EAID_7A147E0A_C6B9_4037_AC76_E08AFCCA83CA" name="OrderInsResource" UMLType="Class"/><EAStub xmi.id="EAID_6E65998C_64E7_4d93_943D_0D48CCC716F2" name="OrderInResource" UMLType="Class"/><EAStub xmi.id="EAID_4552AA43_0F22_48d8_990C_9F55C34EAFA2" name="Product" UMLType="Class"/><EAStub xmi.id="EAID_E971BBB6_4C2F_4889_87F4_D5837581E3DB" name="User" UMLType="Class"/><EAStub xmi.id="EAID_5586CC68_685B_4da4_962B_EA569EAD3143" name="OrderIn" UMLType="Class"/></XMI.extensions></XMI>
